{
	"databaseType": "Sybase",
	"inputEntity": [
		{
			"entityId": "EN_CLIENTEOD_167",
			"module": {
				"moduleId": "FCTRC",
				"moduleName": "FACTURACION"
			},
			"name": "Cliente"
		}
	],
	"inputParameters": [
		{
			"attributeId": "",
			"bddType": "int",
			"dataType": "INT",
			"direction": "in",
			"entityId": "",
			"format": "",
			"name": "@t_trn",
			"type": "CONSTANT",
			"value": "70707285"
		},
		{
			"attributeId": "",
			"bddType": "char",
			"dataType": "CHAR",
			"direction": "in",
			"entityId": "",
			"format": "",
			"name": "@i_operacion",
			"type": "CONSTANT",
			"value": "U"
		},
		{
			"attributeId": "AT39_CEDULAFS167",
			"bddType": "varchar",
			"dataType": "VARCHAR",
			"direction": "in",
			"entityId": "EN_CLIENTEOD_167",
			"format": "",
			"name": "@i_cedula",
			"type": "ATTRIBUTE",
			"value": ""
		},
		{
			"attributeId": "AT93_NOMBREYM167",
			"bddType": "varchar",
			"dataType": "VARCHAR",
			"direction": "in",
			"entityId": "EN_CLIENTEOD_167",
			"format": "",
			"name": "@i_nombre",
			"type": "ATTRIBUTE",
			"value": ""
		},
		{
			"attributeId": "AT29_APELLIOD167",
			"bddType": "varchar",
			"dataType": "VARCHAR",
			"direction": "in",
			"entityId": "EN_CLIENTEOD_167",
			"format": "",
			"name": "@i_apellido",
			"type": "ATTRIBUTE",
			"value": ""
		},
		{
			"attributeId": "AT93_TELEFOON167",
			"bddType": "varchar",
			"dataType": "VARCHAR",
			"direction": "in",
			"entityId": "EN_CLIENTEOD_167",
			"format": "",
			"name": "@i_telefono",
			"type": "ATTRIBUTE",
			"value": ""
		},
		{
			"attributeId": "AT72_DIRECCOI167",
			"bddType": "varchar",
			"dataType": "VARCHAR",
			"direction": "in",
			"entityId": "EN_CLIENTEOD_167",
			"format": "",
			"name": "@i_direccion",
			"type": "ATTRIBUTE",
			"value": ""
		},
		{
			"attributeId": "",
			"bddType": "int",
			"dataType": "INT",
			"direction": "out",
			"entityId": "",
			"format": "",
			"name": "@o_codigo",
			"type": "CONSTANT",
			"value": "0"
		}
	],
	"name": "BLI_ActualizarCliente",
	"outputEntity": [
	],
	"outputParameters": [
	],
	"patternId": "BLI3200_bli_actualizarcliente",
	"patternName": "BLI_ActualizarCliente",
	"patternType": "Bli",
	"queries": [
	],
	"resultSets": [
	],
	"returnEntity": [
	],
	"serverName": "CENTRAL",
	"serviceID": "cobis.sp_grupod_cliente",
	"type": "SP",
	"typeMapping": "MAPJava"
}
